rtl/policy_gate.v
module policy_gate (
    input clk,
    input rst,
    
    // Inputs
    input reflex_active,           // From SNN Core (The Veto)
    input signed [15:0] policy_torque, // From Python/AI (The Request)
    
    // Configuration
    input signed [15:0] safe_torque,   // e.g., 0 for Stop, or Hold value
    input [15:0] lock_duration,        // How long to hold brake (in cycles)

    // Output to Motor
    output reg signed [15:0] final_command,
    output reg override_status         // For logging: "Did we veto?"
);

    reg [15:0] lock_counter;
    reg locked;

    always @(posedge clk or posedge rst) begin
        if (rst) begin
            final_command <= 0;
            override_status <= 0;
            lock_counter <= 0;
            locked <= 0;
        end else begin
            
            // 1. Lock Logic (Hysteresis)
            if (reflex_active) begin
                locked <= 1;
                lock_counter <= lock_duration; // Reset timer
            end else if (lock_counter > 0) begin
                locked <= 1;
                lock_counter <= lock_counter - 1;
            end else begin
                locked <= 0;
            end

            // 2. Gate Logic (The Veto)
            if (locked) begin
                final_command <= safe_torque; // OVERRIDE!
                override_status <= 1;
            end else begin
                final_command <= policy_torque; // Pass-through
                override_status <= 0;
            end
        end
    end

endmodule

rtl/snn_reflex_core.v
module snn_reflex_core (
    input clk,
    input rst,
    
    // Spikes from Encoder
    input spike_drift,
    input spike_spread,
    input spike_shock,

    // Synaptic Weights
    input [15:0] w_drift,  
    input [15:0] w_spread, 
    input [15:0] w_shock,  
    
    // Neuron Properties
    input [15:0] leak_rate,
    input [15:0] threshold,

    // The Output
    output reg reflex_active,
    output reg [15:0] v_mem
);

    // Internal Potential Accumulator
    reg signed [19:0] potential;

    // --- FIX: Calculate Input Current here (Combinational Logic) ---
    // We sum up the weights of any active spikes using a wire
    wire signed [19:0] input_current;
    assign input_current = (spike_drift  ? w_drift  : 16'd0) + 
                           (spike_spread ? w_spread : 16'd0) + 
                           (spike_shock  ? w_shock  : 16'd0);

    always @(posedge clk or posedge rst) begin
        if (rst) begin
            potential <= 0;
            reflex_active <= 0;
            v_mem <= 0;
        end else begin
            
            // 1. Check for Firing (Immediate Reflex)
            if (potential >= threshold) begin
                reflex_active <= 1;      // Fire!
                potential <= 0;          // Reset
            end else begin
                reflex_active <= 0;
                
                // 2. Leaky Integration Logic
                // New Potential = Old + Input - Leak
                if (potential + input_current > leak_rate) begin
                    potential <= potential + input_current - leak_rate;
                end else begin
                    potential <= 0;      // Floor at 0
                end
            end
            
            // Debug Output
            v_mem <= potential[15:0];
        end
    end

endmodule

rtl/spike_encoder.v
module spike_encoder (
    input clk,
    input rst,
    input line_sync,            // Update only when new metrics arrive (end of line)
    
    // Inputs from Symmetry Monitor
    input signed [23:0] drift_in,
    input signed [31:0] spread_in,
    input signed [23:0] change_in,

    // Configuration (Sensitivity)
    // Lower threshold = More sensitive (Fires faster)
    input [23:0] drift_thresh, 
    input [31:0] spread_thresh,
    input [23:0] change_thresh,

    // Spike Outputs to SNN
    output reg spike_drift,
    output reg spike_spread,
    output reg spike_shock      // The "Jerk" spike
);

    // Internal Accumulators (The "Potentials")
    reg [24:0] acc_drift;
    reg [32:0] acc_spread;
    reg [24:0] acc_change;

    // Helper: Absolute Value Function
    function [31:0] abs_val;
        input signed [31:0] val;
        begin
            abs_val = (val < 0) ? -val : val;
        end
    endfunction

    always @(posedge clk or posedge rst) begin
        if (rst) begin
            acc_drift <= 0;
            acc_spread <= 0;
            acc_change <= 0;
            spike_drift <= 0;
            spike_spread <= 0;
            spike_shock <= 0;
        end else begin
            // Default: Spikes are single-cycle pulses
            spike_drift <= 0;
            spike_spread <= 0;
            spike_shock <= 0;

            if (line_sync) begin
                // 1. Encode Drift (First Moment)
                // Add absolute error to the accumulator
                // Logic: Error acts like "Current" charging a capacitor
                if (acc_drift >= drift_thresh) begin
                    spike_drift <= 1;
                    acc_drift <= abs_val(drift_in); // Reset with residual? Or zero? 
                                                    // "Standard" is subtract thresh, 
                                                    // but Reset is safer for Reflexes (prevents runaways)
                end else begin
                    acc_drift <= acc_drift + abs_val(drift_in);
                end

                // 2. Encode Spread (Second Moment)
                if (acc_spread >= spread_thresh) begin
                    spike_spread <= 1;
                    acc_spread <= abs_val(spread_in);
                end else begin
                    acc_spread <= acc_spread + abs_val(spread_in);
                end

                // 3. Encode Shock (Derivative)
                // This is critical. Sudden changes should fire IMMEDIATELY.
                // We give it a "Boost" multiplier if it's very high.
                if (acc_change >= change_thresh) begin
                    spike_shock <= 1;
                    acc_change <= abs_val(change_in);
                end else begin
                    acc_change <= acc_change + abs_val(change_in);
                end
            end
        end
    end

endmodule

rtl/symmetry_monitor.v
module symmetry_monitor (
    input clk,
    input rst,
    
    // Streaming Interface
    input valid_pixel,        // High when pixel data is valid
    input end_of_line,        // High for 1 tick at end of a row (sync)
    input [7:0] pixel_val,    // Intensity/Depth (I)
    input [9:0] x_coord,      // Current X position
    input [9:0] center_x,     // Target Center (Set-point)

    // Control-Relevant Outputs (The "Reflex Trigger" signals)
    output reg signed [23:0] drift_metric,     // First Moment Imbalance
    output reg signed [31:0] spread_metric,    // Second Moment Imbalance
    output reg signed [23:0] sudden_change     // Temporal Derivative
);

    // --- Internal Accumulators ---
    // m1: First Moment (Mass Balance)
    // m2: Second Moment (Variance/Spread)
    reg signed [23:0] acc_m1; 
    reg signed [31:0] acc_m2;
    
    // History for Derivative Calculation
    reg signed [23:0] prev_m1_final;

    // --- Combinational Math (DSP Slices) ---
    // Calculate distance from center (signed)
    wire signed [10:0] dist; 
    assign dist = $signed({1'b0, x_coord}) - $signed({1'b0, center_x});

    // Moment Terms
    wire signed [19:0] term_1; // Pixel * Dist
    wire signed [29:0] term_2; // Pixel * Dist^2

    // Q: Why separate terms? 
    // A: To optimize timing, synthesis can map these to DSP48 blocks.
    assign term_1 = $signed({1'b0, pixel_val}) * dist;
    assign term_2 = term_1 * dist; // Efficiently reuse term_1 mult

    // --- Main Logic ---
    always @(posedge clk or posedge rst) begin
        if (rst) begin
            acc_m1 <= 0;
            acc_m2 <= 0;
            prev_m1_final <= 0;
            drift_metric <= 0;
            spread_metric <= 0;
            sudden_change <= 0;
        end else begin
            
            // 1. Accumulate Line Data (Streaming)
            if (valid_pixel) begin
                acc_m1 <= acc_m1 + term_1;
                
                // For m2 (Spread), we want imbalance. 
                // A perfectly symmetric object has equal spread on L and R.
                // So we actually want to know if the Spread is ASYMMETRIC?
                // Or just total spread change? 
                // Standard Reflex: Track total spread (deformation) or L-vs-R spread.
                // Here, we track L-vs-R spread difference by keeping the sign of 'dist'.
                // If dist is negative (Left), term_2 becomes negative? 
                // Wait: term_2 = term_1 * dist. 
                // Left: (Neg * Neg) * Neg = Neg? No.
                // Left: (Pix * -d) * -d = Pix * d^2. Always Positive.
                // To detect Spread IMBALANCE, we need to manually apply sign.
                // If Left, subtract. If Right, add.
                if (dist < 0) 
                    acc_m2 <= acc_m2 - $signed({1'b0, pixel_val}) * (dist * dist);
                else
                    acc_m2 <= acc_m2 + $signed({1'b0, pixel_val}) * (dist * dist);
            end

            // 2. End of Line Processing (Reflex Update)
            if (end_of_line) begin
                // Update Outputs
                drift_metric  <= acc_m1;
                spread_metric <= acc_m2;
                
                // Calculate Derivative (Jerk)
                // How much did the Drift change since the last line/frame?
                // This catches sudden slips.
                sudden_change <= acc_m1 - prev_m1_final;
                
                // Store history
                prev_m1_final <= acc_m1;
                
                // Reset Accumulators for next line
                acc_m1 <= 0;
                acc_m2 <= 0;
            end
        end
    end

endmodule

rtl/top_reflex_system.v
module top_reflex_system (
    input clk,
    input rst,
    
    // 1. Sensor Input (From Event Camera/Camera)
    input valid_pixel,
    input end_of_line,
    input [7:0] pixel_val,
    input [9:0] x_coord,
    input [9:0] center_x, // Target center
    
    // 2. Policy Input (From Python AI)
    input signed [15:0] policy_torque,

    // 3. Tunable Parameters (Configuration)
    input [23:0] drift_thresh,
    input [31:0] spread_thresh,
    input [23:0] change_thresh,
    input [15:0] w_drift,
    input [15:0] w_spread,
    input [15:0] w_shock,
    input [15:0] snn_threshold,
    input [15:0] safe_torque,

    // 4. Output (To Motor)
    output signed [15:0] final_command,
    output reflex_active,      // Debug: Did SNN fire?
    output override_status     // Debug: Is Gate locking?
);

    // --- Interconnect Wires ---
    wire signed [23:0] drift_metric;
    wire signed [31:0] spread_metric;
    wire signed [23:0] sudden_change;

    wire spike_drift, spike_spread, spike_shock;
    wire snn_fire_signal;

    // --- Module A: Symmetry Monitor ---
    symmetry_monitor mon_inst (
        .clk(clk), .rst(rst),
        .valid_pixel(valid_pixel), .end_of_line(end_of_line),
        .pixel_val(pixel_val), .x_coord(x_coord), .center_x(center_x),
        .drift_metric(drift_metric),
        .spread_metric(spread_metric),
        .sudden_change(sudden_change)
    );

    // --- Module B: Spike Encoder ---
    spike_encoder enc_inst (
        .clk(clk), .rst(rst), .line_sync(end_of_line),
        .drift_in(drift_metric), .spread_in(spread_metric), .change_in(sudden_change),
        .drift_thresh(drift_thresh), .spread_thresh(spread_thresh), .change_thresh(change_thresh),
        .spike_drift(spike_drift), .spike_spread(spike_spread), .spike_shock(spike_shock)
    );

    // --- Module C: SNN Reflex Core ---
    snn_reflex_core snn_inst (
        .clk(clk), .rst(rst),
        .spike_drift(spike_drift), .spike_spread(spike_spread), .spike_shock(spike_shock),
        .w_drift(w_drift), .w_spread(w_spread), .w_shock(w_shock),
        .leak_rate(16'd5),          // Hardcoded or make input
        .threshold(snn_threshold),
        .reflex_active(snn_fire_signal),
        .v_mem()                    // Disconnected for now
    );

    // --- Module D: Policy Gate ---
    policy_gate gate_inst (
        .clk(clk), .rst(rst),
        .reflex_active(snn_fire_signal),
        .policy_torque(policy_torque),
        .safe_torque(safe_torque),
        .lock_duration(16'd100),    // Lock for 100 cycles
        .final_command(final_command),
        .override_status(override_status)
    );

    // Expose internal signal for debug
    assign reflex_active = snn_fire_signal;

endmodule

tb/tb_reflex_system.v
`timescale 1ns / 1ps

module tb_reflex_system;

    reg clk, rst;
    
    // Camera Inputs
    reg valid_pixel;
    reg end_of_line;
    reg [7:0] pixel_val;
    reg [9:0] x_coord;
    reg [9:0] center_x;
    
    // Policy Input
    reg signed [15:0] policy_torque;

    // Config Inputs
    reg [23:0] drift_thresh;
    reg [31:0] spread_thresh;
    reg [23:0] change_thresh;
    reg [15:0] w_drift, w_spread, w_shock;
    reg [15:0] snn_threshold;
    reg [15:0] safe_torque;

    // Outputs
    wire signed [15:0] final_command;
    wire reflex_active;
    wire override_status;

    // Instantiate Top Module
    top_reflex_system dut (
        .clk(clk), .rst(rst),
        .valid_pixel(valid_pixel), .end_of_line(end_of_line),
        .pixel_val(pixel_val), .x_coord(x_coord), .center_x(center_x),
        .policy_torque(policy_torque),
        .drift_thresh(drift_thresh), .spread_thresh(spread_thresh), .change_thresh(change_thresh),
        .w_drift(w_drift), .w_spread(w_spread), .w_shock(w_shock),
        .snn_threshold(snn_threshold), .safe_torque(safe_torque),
        .final_command(final_command),
        .reflex_active(reflex_active),
        .override_status(override_status)
    );

    // Clock
    always #5 clk = ~clk;

    // Helper task to simulate one "Pixel"
    task send_pixel;
        input [9:0] x;
        input [7:0] val;
        begin
            valid_pixel = 1;
            x_coord = x;
            pixel_val = val;
            #10; // 1 cycle
            valid_pixel = 0;
        end
    endtask

    // Helper task to simulate a whole line of an object
    // center_pos: where the object actually is
    task send_object_line;
        input [9:0] actual_center;
        integer i;
        begin
            // Send a block of pixels around the actual center
            // Simulate a 10-pixel wide object
            for (i = -5; i < 5; i = i + 1) begin
                send_pixel(actual_center + i, 8'd100); // Intensity 100
            end
            // End of line sync
            #10;
            end_of_line = 1;
            #10;
            end_of_line = 0;
            #10;
        end
    endtask

    initial begin
        $dumpfile("reflex_wave.vcd");
        $dumpvars(0, tb_reflex_system);

        // 1. Initialize
        clk = 0; rst = 1;
        valid_pixel = 0; end_of_line = 0; pixel_val = 0; x_coord = 0;
        center_x = 300; // Target is pixel 300
        
        // AI wants to move full speed
        policy_torque = 16'd1000; 
        safe_torque = 16'd0; // Stop if unsafe

        // Setup Thresholds (Tuning)
        drift_thresh = 24'd500;   // Sensitivity
        spread_thresh = 32'd1000;
        change_thresh = 24'd200;
        
        // SNN Weights
        w_drift = 16'd50;
        w_spread = 16'd10;
        w_shock = 16'd200; // Shock has high weight
        snn_threshold = 16'd150; // Fire when potential > 150

        #20 rst = 0;

        // 2. PHASE 1: NORMAL (Object is Centered at 300)
        // Send 5 lines. Drift should be ~0. SNN should be quiet.
        repeat(5) begin
            send_object_line(300); // Object is exactly where it should be
        end

        // 3. PHASE 2: SLIP START (Object shifts to 310)
        // This causes Drift error.
        repeat(5) begin
            send_object_line(310); 
        end

        // 4. PHASE 3: MAJOR SLIP (Object shifts to 350)
        // This causes HUGE Drift + Shock. SNN should FIRE here.
        repeat(5) begin
            send_object_line(350); 
        end

        #100;
        $finish;
    end

endmodule

reflex_wave.vcd
$date
	Sat Jan 10 20:02:22 2026
$end
$version
	Icarus Verilog
$end
$timescale
	1ps
$end
$scope module tb_reflex_system $end
$var wire 1 ! reflex_active $end
$var wire 1 " override_status $end
$var wire 16 # final_command [15:0] $end
$var reg 10 $ center_x [9:0] $end
$var reg 24 % change_thresh [23:0] $end
$var reg 1 & clk $end
$var reg 24 ' drift_thresh [23:0] $end
$var reg 1 ( end_of_line $end
$var reg 8 ) pixel_val [7:0] $end
$var reg 16 * policy_torque [15:0] $end
$var reg 1 + rst $end
$var reg 16 , safe_torque [15:0] $end
$var reg 16 - snn_threshold [15:0] $end
$var reg 32 . spread_thresh [31:0] $end
$var reg 1 / valid_pixel $end
$var reg 16 0 w_drift [15:0] $end
$var reg 16 1 w_shock [15:0] $end
$var reg 16 2 w_spread [15:0] $end
$var reg 10 3 x_coord [9:0] $end
$scope module dut $end
$var wire 10 4 center_x [9:0] $end
$var wire 24 5 change_thresh [23:0] $end
$var wire 1 & clk $end
$var wire 24 6 drift_thresh [23:0] $end
$var wire 1 ( end_of_line $end
$var wire 8 7 pixel_val [7:0] $end
$var wire 16 8 policy_torque [15:0] $end
$var wire 1 ! reflex_active $end
$var wire 1 + rst $end
$var wire 16 9 safe_torque [15:0] $end
$var wire 16 : snn_threshold [15:0] $end
$var wire 32 ; spread_thresh [31:0] $end
$var wire 1 / valid_pixel $end
$var wire 16 < w_drift [15:0] $end
$var wire 16 = w_shock [15:0] $end
$var wire 16 > w_spread [15:0] $end
$var wire 10 ? x_coord [9:0] $end
$var wire 24 @ sudden_change [23:0] $end
$var wire 32 A spread_metric [31:0] $end
$var wire 1 B spike_spread $end
$var wire 1 C spike_shock $end
$var wire 1 D spike_drift $end
$var wire 1 E snn_fire_signal $end
$var wire 1 " override_status $end
$var wire 16 F final_command [15:0] $end
$var wire 24 G drift_metric [23:0] $end
$scope module enc_inst $end
$var wire 24 H change_thresh [23:0] $end
$var wire 1 & clk $end
$var wire 24 I drift_thresh [23:0] $end
$var wire 1 ( line_sync $end
$var wire 1 + rst $end
$var wire 32 J spread_thresh [31:0] $end
$var wire 32 K spread_in [31:0] $end
$var wire 24 L drift_in [23:0] $end
$var wire 24 M change_in [23:0] $end
$var reg 25 N acc_change [24:0] $end
$var reg 25 O acc_drift [24:0] $end
$var reg 33 P acc_spread [32:0] $end
$var reg 1 D spike_drift $end
$var reg 1 C spike_shock $end
$var reg 1 B spike_spread $end
$scope function abs_val $end
$var reg 32 Q val [31:0] $end
$upscope $end
$upscope $end
$scope module gate_inst $end
$var wire 1 & clk $end
$var wire 16 R lock_duration [15:0] $end
$var wire 16 S policy_torque [15:0] $end
$var wire 1 + rst $end
$var wire 16 T safe_torque [15:0] $end
$var wire 1 E reflex_active $end
$var reg 16 U final_command [15:0] $end
$var reg 16 V lock_counter [15:0] $end
$var reg 1 W locked $end
$var reg 1 " override_status $end
$upscope $end
$scope module mon_inst $end
$var wire 10 X center_x [9:0] $end
$var wire 1 & clk $end
$var wire 1 ( end_of_line $end
$var wire 8 Y pixel_val [7:0] $end
$var wire 1 + rst $end
$var wire 1 / valid_pixel $end
$var wire 10 Z x_coord [9:0] $end
$var wire 30 [ term_2 [29:0] $end
$var wire 20 \ term_1 [19:0] $end
$var wire 11 ] dist [10:0] $end
$var reg 24 ^ acc_m1 [23:0] $end
$var reg 32 _ acc_m2 [31:0] $end
$var reg 24 ` drift_metric [23:0] $end
$var reg 24 a prev_m1_final [23:0] $end
$var reg 32 b spread_metric [31:0] $end
$var reg 24 c sudden_change [23:0] $end
$upscope $end
$scope module snn_inst $end
$var wire 1 & clk $end
$var wire 16 d leak_rate [15:0] $end
$var wire 1 + rst $end
$var wire 1 D spike_drift $end
$var wire 1 C spike_shock $end
$var wire 1 B spike_spread $end
$var wire 16 e threshold [15:0] $end
$var wire 16 f w_drift [15:0] $end
$var wire 16 g w_shock [15:0] $end
$var wire 16 h w_spread [15:0] $end
$var wire 20 i input_current [19:0] $end
$var reg 20 j potential [19:0] $end
$var reg 1 E reflex_active $end
$var reg 16 k v_mem [15:0] $end
$upscope $end
$upscope $end
$scope task send_object_line $end
$var reg 10 l actual_center [9:0] $end
$var integer 32 m i [31:0] $end
$upscope $end
$scope task send_pixel $end
$var reg 8 n val [7:0] $end
$var reg 10 o x [9:0] $end
$upscope $end
$upscope $end
$enddefinitions $end
$comment Show the parameter values. $end
$dumpall
$end
#0
$dumpvars
bx o
bx n
bx m
bx l
b0 k
b0 j
b0 i
b1010 h
b11001000 g
b110010 f
b10010110 e
b101 d
b0 c
b0 b
b0 a
b0 `
b0 _
b0 ^
b11011010100 ]
b0 \
b0 [
b0 Z
b0 Y
b100101100 X
0W
b0 V
b0 U
b0 T
b1111101000 S
b1100100 R
bx Q
b0 P
b0 O
b0 N
b0 M
b0 L
b0 K
b1111101000 J
b111110100 I
b11001000 H
b0 G
b0 F
0E
0D
0C
0B
b0 A
b0 @
b0 ?
b1010 >
b11001000 =
b110010 <
b1111101000 ;
b10010110 :
b0 9
b1111101000 8
b0 7
b111110100 6
b11001000 5
b100101100 4
b0 3
b1010 2
b11001000 1
b110010 0
0/
b1111101000 .
b10010110 -
b0 ,
1+
b1111101000 *
b0 )
0(
b111110100 '
0&
b11001000 %
b100101100 $
b0 #
0"
0!
$end
#5000
1&
#10000
0&
#15000
1&
#20000
0&
b100111000100 [
b11111111111000001100 \
b1100100 )
b1100100 7
b1100100 Y
b11111111011 ]
b100100111 3
b100100111 ?
b100100111 Z
1/
b1100100 n
b100100111 o
b11111111111111111111111111111011 m
b100101100 l
0+
#25000
b1111101000 #
b1111101000 F
b1111101000 U
b11111111111111111111011000111100 _
b111111111111111000001100 ^
1&
#30000
0&
b11111111111001110000 \
b11001000000 [
b11111111100 ]
b100101000 3
b100101000 ?
b100101000 Z
b100101000 o
b11111111111111111111111111111100 m
1/
#35000
b11111111111111111110111111111100 _
b111111111111110001111100 ^
1&
#40000
0&
b11111111111011010100 \
b1110000100 [
b11111111101 ]
b100101001 3
b100101001 ?
b100101001 Z
b100101001 o
b11111111111111111111111111111101 m
1/
#45000
b11111111111111111110110001111000 _
b111111111111101101010000 ^
1&
#50000
0&
b11111111111100111000 \
b110010000 [
b11111111110 ]
b100101010 3
b100101010 ?
b100101010 Z
b100101010 o
b11111111111111111111111111111110 m
1/
#55000
b11111111111111111110101011101000 _
b111111111111101010001000 ^
1&
#60000
0&
b11111111111110011100 \
b1100100 [
b11111111111 ]
b100101011 3
b100101011 ?
b100101011 Z
b100101011 o
b11111111111111111111111111111111 m
1/
#65000
b11111111111111111110101010000100 _
b111111111111101000100100 ^
1&
#70000
0&
b0 \
b0 [
b0 ]
b100101100 3
b100101100 ?
b100101100 Z
b100101100 o
b0 m
1/
#75000
1&
#80000
0&
b1100100 [
b1100100 \
b1 ]
b100101101 3
b100101101 ?
b100101101 Z
b100101101 o
b1 m
1/
#85000
b11111111111111111110101011101000 _
b111111111111101010001000 ^
1&
#90000
0&
b11001000 \
b110010000 [
b10 ]
b100101110 3
b100101110 ?
b100101110 Z
b100101110 o
b10 m
1/
#95000
b11111111111111111110110001111000 _
b111111111111101101010000 ^
1&
#100000
0&
b100101100 \
b1110000100 [
b11 ]
b100101111 3
b100101111 ?
b100101111 Z
b100101111 o
b11 m
1/
#105000
b11111111111111111110111111111100 _
b111111111111110001111100 ^
1&
#110000
0&
b110010000 \
b11001000000 [
b100 ]
b100110000 3
b100110000 ?
b100110000 Z
b100110000 o
b100 m
1/
#115000
b11111111111111111111011000111100 _
b111111111111111000001100 ^
1&
#120000
0&
b101 m
0/
#125000
1&
#130000
0&
1(
#135000
b0 _
b0 ^
b111111111111111000001100 a
b111111111111111000001100 @
b111111111111111000001100 M
b111111111111111000001100 c
b11111111111111111111011000111100 A
b11111111111111111111011000111100 K
b11111111111111111111011000111100 b
b111111111111111000001100 G
b111111111111111000001100 L
b111111111111111000001100 `
b0 Q
1&
#140000
0&
0(
#145000
1&
#150000
0&
b11111111111000001100 \
b100111000100 [
b11111111011 ]
b100100111 3
b100100111 ?
b100100111 Z
1/
b100100111 o
b11111111111111111111111111111011 m
#155000
b11111111111111111111011000111100 _
b111111111111111000001100 ^
1&
#160000
0&
b11111111111001110000 \
b11001000000 [
b11111111100 ]
b100101000 3
b100101000 ?
b100101000 Z
b100101000 o
b11111111111111111111111111111100 m
1/
#165000
b11111111111111111110111111111100 _
b111111111111110001111100 ^
1&
#170000
0&
b11111111111011010100 \
b1110000100 [
b11111111101 ]
b100101001 3
b100101001 ?
b100101001 Z
b100101001 o
b11111111111111111111111111111101 m
1/
#175000
b11111111111111111110110001111000 _
b111111111111101101010000 ^
1&
#180000
0&
b11111111111100111000 \
b110010000 [
b11111111110 ]
b100101010 3
b100101010 ?
b100101010 Z
b100101010 o
b11111111111111111111111111111110 m
1/
#185000
b11111111111111111110101011101000 _
b111111111111101010001000 ^
1&
#190000
0&
b11111111111110011100 \
b1100100 [
b11111111111 ]
b100101011 3
b100101011 ?
b100101011 Z
b100101011 o
b11111111111111111111111111111111 m
1/
#195000
b11111111111111111110101010000100 _
b111111111111101000100100 ^
1&
#200000
0&
b0 \
b0 [
b0 ]
b100101100 3
b100101100 ?
b100101100 Z
b100101100 o
b0 m
1/
#205000
1&
#210000
0&
b1100100 [
b1100100 \
b1 ]
b100101101 3
b100101101 ?
b100101101 Z
b100101101 o
b1 m
1/
#215000
b11111111111111111110101011101000 _
b111111111111101010001000 ^
1&
#220000
0&
b11001000 \
b110010000 [
b10 ]
b100101110 3
b100101110 ?
b100101110 Z
b100101110 o
b10 m
1/
#225000
b11111111111111111110110001111000 _
b111111111111101101010000 ^
1&
#230000
0&
b100101100 \
b1110000100 [
b11 ]
b100101111 3
b100101111 ?
b100101111 Z
b100101111 o
b11 m
1/
#235000
b11111111111111111110111111111100 _
b111111111111110001111100 ^
1&
#240000
0&
b110010000 \
b11001000000 [
b100 ]
b100110000 3
b100110000 ?
b100110000 Z
b100110000 o
b100 m
1/
#245000
b11111111111111111111011000111100 _
b111111111111111000001100 ^
1&
#250000
0&
b101 m
0/
#255000
1&
#260000
0&
1(
#265000
b111110100 N
b100111000100 P
b111110100 O
b0 _
b0 ^
b0 @
b0 M
b0 c
b11111111111111111111111000001100 Q
1&
#270000
0&
0(
#275000
1&
#280000
0&
b11111111111000001100 \
b100111000100 [
b11111111011 ]
b100100111 3
b100100111 ?
b100100111 Z
1/
b100100111 o
b11111111111111111111111111111011 m
#285000
b11111111111111111111011000111100 _
b111111111111111000001100 ^
1&
#290000
0&
b11111111111001110000 \
b11001000000 [
b11111111100 ]
b100101000 3
b100101000 ?
b100101000 Z
b100101000 o
b11111111111111111111111111111100 m
1/
#295000
b11111111111111111110111111111100 _
b111111111111110001111100 ^
1&
#300000
0&
b11111111111011010100 \
b1110000100 [
b11111111101 ]
b100101001 3
b100101001 ?
b100101001 Z
b100101001 o
b11111111111111111111111111111101 m
1/
#305000
b11111111111111111110110001111000 _
b111111111111101101010000 ^
1&
#310000
0&
b11111111111100111000 \
b110010000 [
b11111111110 ]
b100101010 3
b100101010 ?
b100101010 Z
b100101010 o
b11111111111111111111111111111110 m
1/
#315000
b11111111111111111110101011101000 _
b111111111111101010001000 ^
1&
#320000
0&
b11111111111110011100 \
b1100100 [
b11111111111 ]
b100101011 3
b100101011 ?
b100101011 Z
b100101011 o
b11111111111111111111111111111111 m
1/
#325000
b11111111111111111110101010000100 _
b111111111111101000100100 ^
1&
#330000
0&
b0 \
b0 [
b0 ]
b100101100 3
b100101100 ?
b100101100 Z
b100101100 o
b0 m
1/
#335000
1&
#340000
0&
b1100100 [
b1100100 \
b1 ]
b100101101 3
b100101101 ?
b100101101 Z
b100101101 o
b1 m
1/
#345000
b11111111111111111110101011101000 _
b111111111111101010001000 ^
1&
#350000
0&
b11001000 \
b110010000 [
b10 ]
b100101110 3
b100101110 ?
b100101110 Z
b100101110 o
b10 m
1/
#355000
b11111111111111111110110001111000 _
b111111111111101101010000 ^
1&
#360000
0&
b100101100 \
b1110000100 [
b11 ]
b100101111 3
b100101111 ?
b100101111 Z
b100101111 o
b11 m
1/
#365000
b11111111111111111110111111111100 _
b111111111111110001111100 ^
1&
#370000
0&
b110010000 \
b11001000000 [
b100 ]
b100110000 3
b100110000 ?
b100110000 Z
b100110000 o
b100 m
1/
#375000
b11111111111111111111011000111100 _
b111111111111111000001100 ^
1&
#380000
0&
b101 m
0/
#385000
1&
#390000
0&
1(
#395000
b100000100 i
b0 _
b0 ^
b0 N
1C
1B
1D
b0 Q
1&
#400000
0&
0(
#405000
b0 i
b11111111 j
0C
0B
0D
1&
#410000
0&
b11111111111000001100 \
b100111000100 [
b11111111011 ]
b100100111 3
b100100111 ?
b100100111 Z
1/
b100100111 o
b11111111111111111111111111111011 m
#415000
b11111111111111111111011000111100 _
b111111111111111000001100 ^
b11111111 k
b0 j
1!
1E
1&
#420000
0&
b11111111111001110000 \
b11001000000 [
b11111111100 ]
b100101000 3
b100101000 ?
b100101000 Z
b100101000 o
b11111111111111111111111111111100 m
1/
#425000
b1100100 V
1W
b0 k
0!
0E
b11111111111111111110111111111100 _
b111111111111110001111100 ^
1&
#430000
0&
b11111111111011010100 \
b1110000100 [
b11111111101 ]
b100101001 3
b100101001 ?
b100101001 Z
b100101001 o
b11111111111111111111111111111101 m
1/
#435000
b11111111111111111110110001111000 _
b111111111111101101010000 ^
1"
b0 #
b0 F
b0 U
b1100011 V
1&
#440000
0&
b11111111111100111000 \
b110010000 [
b11111111110 ]
b100101010 3
b100101010 ?
b100101010 Z
b100101010 o
b11111111111111111111111111111110 m
1/
#445000
b1100010 V
b11111111111111111110101011101000 _
b111111111111101010001000 ^
1&
#450000
0&
b11111111111110011100 \
b1100100 [
b11111111111 ]
b100101011 3
b100101011 ?
b100101011 Z
b100101011 o
b11111111111111111111111111111111 m
1/
#455000
b11111111111111111110101010000100 _
b111111111111101000100100 ^
b1100001 V
1&
#460000
0&
b0 \
b0 [
b0 ]
b100101100 3
b100101100 ?
b100101100 Z
b100101100 o
b0 m
1/
#465000
b1100000 V
1&
#470000
0&
b1100100 [
b1100100 \
b1 ]
b100101101 3
b100101101 ?
b100101101 Z
b100101101 o
b1 m
1/
#475000
b11111111111111111110101011101000 _
b111111111111101010001000 ^
b1011111 V
1&
#480000
0&
b11001000 \
b110010000 [
b10 ]
b100101110 3
b100101110 ?
b100101110 Z
b100101110 o
b10 m
1/
#485000
b1011110 V
b11111111111111111110110001111000 _
b111111111111101101010000 ^
1&
#490000
0&
b100101100 \
b1110000100 [
b11 ]
b100101111 3
b100101111 ?
b100101111 Z
b100101111 o
b11 m
1/
#495000
b11111111111111111110111111111100 _
b111111111111110001111100 ^
b1011101 V
1&
#500000
0&
b110010000 \
b11001000000 [
b100 ]
b100110000 3
b100110000 ?
b100110000 Z
b100110000 o
b100 m
1/
#505000
b1011100 V
b11111111111111111111011000111100 _
b111111111111111000001100 ^
1&
#510000
0&
b101 m
0/
#515000
b1011011 V
1&
#520000
0&
1(
#525000
b111100 i
b1011010 V
1B
1D
b0 _
b0 ^
b0 Q
1&
#530000
0&
0(
#535000
b0 i
0B
0D
b110111 j
b1011001 V
1&
#540000
0&
b11111111111000001100 \
b100111000100 [
b11111111011 ]
b100100111 3
b100100111 ?
b100100111 Z
1/
b100100111 o
b11111111111111111111111111111011 m
#545000
b1011000 V
b110111 k
b110010 j
b11111111111111111111011000111100 _
b111111111111111000001100 ^
1&
#550000
0&
b11111111111001110000 \
b11001000000 [
b11111111100 ]
b100101000 3
b100101000 ?
b100101000 Z
b100101000 o
b11111111111111111111111111111100 m
1/
#555000
b11111111111111111110111111111100 _
b111111111111110001111100 ^
b110010 k
b101101 j
b1010111 V
1&
#560000
0&
b11111111111011010100 \
b1110000100 [
b11111111101 ]
b100101001 3
b100101001 ?
b100101001 Z
b100101001 o
b11111111111111111111111111111101 m
1/
#565000
b1010110 V
b101101 k
b101000 j
b11111111111111111110110001111000 _
b111111111111101101010000 ^
1&
#570000
0&
b11111111111100111000 \
b110010000 [
b11111111110 ]
b100101010 3
b100101010 ?
b100101010 Z
b100101010 o
b11111111111111111111111111111110 m
1/
#575000
b11111111111111111110101011101000 _
b111111111111101010001000 ^
b101000 k
b100011 j
b1010101 V
1&
#580000
0&
b11111111111110011100 \
b1100100 [
b11111111111 ]
b100101011 3
b100101011 ?
b100101011 Z
b100101011 o
b11111111111111111111111111111111 m
1/
#585000
b1010100 V
b100011 k
b11110 j
b11111111111111111110101010000100 _
b111111111111101000100100 ^
1&
#590000
0&
b0 \
b0 [
b0 ]
b100101100 3
b100101100 ?
b100101100 Z
b100101100 o
b0 m
1/
#595000
b11110 k
b11001 j
b1010011 V
1&
#600000
0&
b1100100 [
b1100100 \
b1 ]
b100101101 3
b100101101 ?
b100101101 Z
b100101101 o
b1 m
1/
#605000
b1010010 V
b11001 k
b10100 j
b11111111111111111110101011101000 _
b111111111111101010001000 ^
1&
